parsel_get_selector_text/__init__.py
parsel_get_selector_text-0.8.dist-info/LICENSE
parsel_get_selector_text-0.8.dist-info/METADATA
parsel_get_selector_text-0.8.dist-info/WHEEL
parsel_get_selector_text-0.8.dist-info/top_level.txt
parsel_get_selector_text-0.8.dist-info/RECORD
