Metadata-Version: 2.1
Name: parsel_get_selector_text
Version: 0.8
Summary: Extracts all text results from an XPath query on a parsel Selector object.
Author-email: "Carlos A. Planchón" <carlosandresplanchonprestes@gmail.com>
License: MIT License
Project-URL: repository, https://github.com/carlosplanchon/parsel_get_selector_text.git
Keywords: dom,parsel,scraping,xpath
Classifier: Intended Audience :: Developers
Classifier: Topic :: Software Development :: Build Tools
Classifier: License :: OSI Approved :: MIT License
Classifier: Programming Language :: Python :: 3.11
License-File: LICENSE
Requires-Dist: ftfy
Requires-Dist: parsel
Requires-Dist: beautifulsoup4
